bin/__init__.py
bin/das.py
bin/dataset.py
bin/edmIntegrityCheck.py
bin/heppy_batch.py
bin/heppy_check.py
bin/heppy_hadd.py
bin/heppy_interactive.py
bin/heppy_loop.py
bin/pythia_batch.py
heppy/__init__.py
heppy/configuration.py
heppy/analyzers/ChargedHadronsFromB.py
heppy/analyzers/EventByNumber.py
heppy/analyzers/EventFilter.py
heppy/analyzers/EventSkipper.py
heppy/analyzers/GaussianSmearer.py
heppy/analyzers/GlobalEventTreeProducer.py
heppy/analyzers/Gun.py
heppy/analyzers/ImpactParameterJetTag.py
heppy/analyzers/ImpactParameterSmearer.py
heppy/analyzers/IsolationAnalyzer.py
heppy/analyzers/JetEnergyCorrector.py
heppy/analyzers/JetTreeProducer.py
heppy/analyzers/LeptonFsrDresser.py
heppy/analyzers/LeptonicZedBuilder.py
heppy/analyzers/M3Builder.py
heppy/analyzers/METBuilder.py
heppy/analyzers/MTW.py
heppy/analyzers/Masker.py
heppy/analyzers/Matcher.py
heppy/analyzers/Merger.py
heppy/analyzers/P4SumBuilder.py
heppy/analyzers/PDebugger.py
heppy/analyzers/PapasDagPlotter.py
heppy/analyzers/PapasDisplay.py
heppy/analyzers/PapasFromFccsw.py
heppy/analyzers/PapasHistoryPrinter.py
heppy/analyzers/PapasPFBlockBuilder.py
heppy/analyzers/PapasPFReconstructor.py
heppy/analyzers/PapasParticlesComparer.py
heppy/analyzers/PapasSim.py
heppy/analyzers/ParametrizedBTagger.py
heppy/analyzers/ParticleTreeProducer.py
heppy/analyzers/RecoilBuilder.py
heppy/analyzers/ResonanceBuilder.py
heppy/analyzers/ResonanceLegExtractor.py
heppy/analyzers/ResonanceMatcher.py
heppy/analyzers/Selector.py
heppy/analyzers/SingleJetBuilder.py
heppy/analyzers/Subtractor.py
heppy/analyzers/Tagger.py
heppy/analyzers/__init__.py
heppy/analyzers/ntuple.py
heppy/analyzers/roc.py
heppy/analyzers/test_Filter.py
heppy/analyzers/test_Gun.py
heppy/analyzers/test_roc.py
heppy/analyzers/tmp.py
heppy/analyzers/cms/JetReader.py
heppy/analyzers/cms/Reader.py
heppy/analyzers/cms/__init__.py
heppy/analyzers/examples/__init__.py
heppy/analyzers/examples/hzz4l/HTo4lGenTreeProducer.py
heppyfwk-3.0.1.dist-info/LICENSE
heppyfwk-3.0.1.dist-info/METADATA
heppyfwk-3.0.1.dist-info/WHEEL
heppyfwk-3.0.1.dist-info/top_level.txt
heppyfwk-3.0.1.dist-info/RECORD
