Metadata-Version: 2.1
Name: heppyfwk
Version: 3.0.1
Summary: An event processing framework for High Energy Physics.
Home-page: https://github.com/cbernet/heppy
Author: Colin Bernet
Author-email: colin.bernet@gmail.com
License: UNKNOWN
Keywords: particle physics root
Platform: UNKNOWN
Classifier: Development Status :: 5 - Production/Stable
Classifier: Intended Audience :: Science/Research
Classifier: Topic :: Scientific/Engineering :: Physics
Classifier: License :: OSI Approved :: GNU General Public License v3 or later (GPLv3+)
Classifier: Programming Language :: Python :: 2
Classifier: Programming Language :: Python :: 2.6
Classifier: Programming Language :: Python :: 2.7
Requires-Python: <3.0
Requires-Dist: numpy
Requires-Dist: scipy
Requires-Dist: dill
Requires-Dist: gitpython
Requires-Dist: pyyaml
Requires-Dist: ipython
